web_terminal/__init__.py
web_terminal/__main__.py
web_terminal/server.py
web_terminal/shell.py
web_terminal/sugar.py
web_terminal/web_terminal.py
web_terminal/client/3rdpartylicenses.txt
web_terminal/client/5-es2015.762dc762933824588d6a.js
web_terminal/client/5-es5.762dc762933824588d6a.js
web_terminal/client/favicon.ico
web_terminal/client/index.html
web_terminal/client/main-es2015.ad1ace850dd81cc474ac.js
web_terminal/client/main-es5.ad1ace850dd81cc474ac.js
web_terminal/client/polyfills-es2015.1f913f16a2d346cc8bdc.js
web_terminal/client/polyfills-es5.876c3b235a8d317f3437.js
web_terminal/client/runtime-es2015.493537fc70d2a8a82fdd.js
web_terminal/client/runtime-es5.493537fc70d2a8a82fdd.js
web_terminal/client/styles.e8cba8816e74816fe316.css
web_terminal/client/assets/bui.png
web_terminal/client/assets/img/copyIcon.png
web_terminal/client/assets/img/logo.png
web_terminal-0.2.1.dist-info/METADATA
web_terminal-0.2.1.dist-info/WHEEL
web_terminal-0.2.1.dist-info/top_level.txt
web_terminal-0.2.1.dist-info/RECORD
