Metadata-Version: 2.1
Name: web_terminal
Version: 0.2.1
Summary: Web_Terminal is a server that gives an easy web-based interface to a terminal window, with plenty of nice features
Home-page: https://danielle-galvao.github.io/web-terminal/
Maintainer: John Meyer
Maintainer-email: dev@johnmeyer.dev
License: BSD3
Keywords: web,terminal
Platform: UNKNOWN
Classifier: Development Status :: 3 - Alpha
Classifier: Environment :: Console
Classifier: Environment :: Web Environment
Classifier: Intended Audience :: End Users/Desktop
Classifier: Intended Audience :: Developers
Classifier: Intended Audience :: System Administrators
Classifier: License :: OSI Approved :: BSD License
Classifier: Programming Language :: Python :: 3
Classifier: Programming Language :: Python :: 3.4
Classifier: Programming Language :: Python :: 3.5
Classifier: Programming Language :: Python :: 3.6
